hazard_unit.v
module hazard_unit (
    input [4:0] rs1_E, rs2_E,
    input [4:0] rs1_D, rs2_D,
    input [4:0] rd_M, rd_W,
    input reg_write_M, reg_write_W,
    input [1:0] wb_sel_E,
    input pc_src_E,
    input jump_E,
    input [4:0] rd_E,
    
    output reg [1:0] forward_a_E, forward_b_E,
    output stall_F, stall_D,
    output flush_D, flush_E
);
    wire lw_stall;

    always @(*) begin
        if ((rs1_E == rd_M) && reg_write_M && (rs1_E != 0)) 
            forward_a_E = 2'b10;
        else if ((rs1_E == rd_W) && reg_write_W && (rs1_E != 0)) 
            forward_a_E = 2'b01;
        else 
            forward_a_E = 2'b00;

        if ((rs2_E == rd_M) && reg_write_M && (rs2_E != 0)) 
            forward_b_E = 2'b10;
        else if ((rs2_E == rd_W) && reg_write_W && (rs2_E != 0)) 
            forward_b_E = 2'b01;
        else 
            forward_b_E = 2'b00;
    end
    
    assign lw_stall = (wb_sel_E == 2'b01) && (rd_E != 0) &&
                      ((rs1_D == rd_E) || (rs2_D == rd_E));
    
    assign stall_F = lw_stall;
    assign stall_D = lw_stall;

    assign flush_D = pc_src_E || jump_E; 
    assign flush_E = lw_stall || pc_src_E || jump_E;

endmodule

data_mem.v
module data_mem (
    input clk, we,
    input [31:0] addr,
    input [31:0] wd,
    output [31:0] rd
);
    reg [31:0] RAM [0:1023];
    assign rd = RAM[addr[11:2]];

    always @(posedge clk) begin
        if (we) RAM[addr[11:2]] <= wd;
    end
endmodule

alu.v
module alu (
    input [31:0] a, b,
    input [3:0] alu_ctrl,
    output reg [31:0] result,
    output reg zero
);

    always @(*) begin
        case (alu_ctrl)
            4'h0: result = a + b;
            4'h1: result = a - b;
            4'h2: result = a << b[4:0];
            4'h3: result = ($signed(a) < $signed(b)) ? 32'd1 : 32'd0;
            4'h4: result = (a < b) ? 32'd1 : 32'd0;
            4'h5: result = a ^ b;
            4'h6: result = a >> b[4:0];
            4'h7: result = $signed(a) >>> b[4:0];
            4'h8: result = a | b;
            4'h9: result = a & b;
            default: result = 32'b0;
        endcase
        zero = (result == 0);
    end
endmodule

sign_extender.v
module sign_extender (
    input [31:0] inst,
    input [2:0] imm_sel,
    output reg [31:0] imm
);
    always @(*) begin
        case (imm_sel)
            3'b000: imm = {{20{inst[31]}}, inst[31:20]};
            3'b001: imm = {{20{inst[31]}}, inst[31:25], inst[11:7]};
            3'b010: imm = {{19{inst[31]}}, inst[31], inst[7], inst[30:25], inst[11:8], 1'b0};
            3'b011: imm = {inst[31:12], 12'b0};
            3'b100: imm = {{11{inst[31]}}, inst[31], inst[19:12], inst[20], inst[30:21], 1'b0};
            default: imm = 32'b0;
        endcase
    end
endmodule

register_file.v
module register_file (
    input clk,
    input rst_n,
    input we,
    input [4:0] rs1, rs2, rd,
    input [31:0] wd,
    output [31:0] rd1, rd2
);
    reg [31:0] regs [0:31];
    integer i;

    assign rd1 = (rs1 == 5'b0) ? 32'b0 : regs[rs1];
    assign rd2 = (rs2 == 5'b0) ? 32'b0 : regs[rs2];

    always @(negedge clk or negedge rst_n) begin
        if (!rst_n) begin
            for (i = 0; i < 32; i = i + 1) regs[i] <= 32'b0;
        end else if (we && (rd != 5'b0)) begin
            regs[rd] <= wd;
        end
    end
endmodule

controller.v
module controller (
    input [6:0] opcode,
    input [2:0] funct3,
    input [6:0] funct7,
    output reg rf_we,
    output reg mem_we,
    output reg [1:0] wb_sel,
    output reg alu_src,
    output reg [2:0] imm_sel,
    output reg [3:0] alu_ctrl,
    output reg branch,
    output reg jump
);
    always @(*) begin
        rf_we = 0; 
        mem_we = 0; 
        wb_sel = 0; 
        alu_src = 0; 
        imm_sel = 0; 
        alu_ctrl = 0;
        branch =0;
        jump = 0;

        case (opcode)
            7'b0110011: begin
                rf_we = 1; alu_src = 0; wb_sel = 0;
                case (funct3)
                    3'b000: alu_ctrl = (funct7[5]) ? 4'h1 : 4'h0;
                    3'b001: alu_ctrl = 4'h2;
                    3'b010: alu_ctrl = 4'h3;
                    3'b100: alu_ctrl = 4'h5;
                    3'b101: alu_ctrl = (funct7[5]) ? 4'h7 : 4'h6;
                    3'b110: alu_ctrl = 4'h8;
                    3'b111: alu_ctrl = 4'h9;
                    default: alu_ctrl = 4'h0;
                endcase
            end
            7'b0010011: begin
                rf_we = 1; alu_src = 1; wb_sel = 0; imm_sel = 3'b000;
                case (funct3)
                    3'b000: alu_ctrl = 4'h0;
                    3'b010: alu_ctrl = 4'h3;
                    3'b100: alu_ctrl = 4'h5;
                    3'b110: alu_ctrl = 4'h8;
                    3'b111: alu_ctrl = 4'h9;
                    default: alu_ctrl = 4'h0;
                endcase
            end
            7'b1100011: begin
                rf_we   = 0;
                mem_we  = 0;
                alu_src = 0;
                wb_sel  = 0;
                imm_sel = 3'b010;
                alu_ctrl = 4'h1;
                branch  = 1;
                jump    = 0;
            end
            7'b1101111: begin
                rf_we   = 1;
                mem_we  = 0;
                alu_src = 0;
                wb_sel  = 2'b10;
                imm_sel = 3'b100;
                alu_ctrl = 4'h0;
                branch  = 0;
                jump    = 1;
            end
            7'b0000011: begin
                rf_we = 1; 
                alu_src = 1; 
                wb_sel = 2'b01; 
                imm_sel = 3'b000;
                mem_we = 0; 
                alu_ctrl = 4'h0;
            end
            7'b0100011: begin
                rf_we = 0; 
                alu_src = 1; 
                imm_sel = 3'b001;
                mem_we = 1; 
                alu_ctrl = 4'h0;
            end
            7'b0110111: begin
                 rf_we = 1; 
                 alu_src = 1; 
                 wb_sel = 2'b00; 
                 imm_sel = 3'b011;
            end
        endcase
    end
endmodule

instruction_mem.v
module instruction_mem (
    input [31:0] addr,
    output [31:0] inst
);
    reg [31:0] RAM [0:1023];
    assign inst = RAM[addr[11:2]];
endmodule

rv_pl.v
`include "alu.v"
`include "controller.v"
`include "data_mem.v"
`include "hazard_unit.v"
`include "instruction_mem.v"
`include "register_file.v"
`include "sign_extender.v"

module rv_pl (
    input clk,
    input rst_n
);
    wire stall_F, stall_D, flush_D, flush_E;
    wire [1:0] forward_a_E, forward_b_E;

    reg [31:0] PC;
    wire [31:0] PC_Next, PC_Plus4, PC_Target_E, Instr;
    wire pc_src_E, jump_E; 

    assign PC_Plus4 = PC + 4;
    assign PC_Next = (pc_src_E || jump_E) ? PC_Target_E : PC_Plus4;

    always @(posedge clk or negedge rst_n) begin
        if (!rst_n) PC <= 0;
        else if (!stall_F) PC <= PC_Next;
    end

    instruction_mem IMEM (.addr(PC), .inst(Instr));

    reg [31:0] ID_PC, ID_Instr;
    always @(posedge clk or negedge rst_n) begin
        if (!rst_n) begin 
            ID_PC <= 0; 
            ID_Instr <= 0; 
        end
        else if (flush_D) begin 
            ID_PC <= 0; 
            ID_Instr <= 0; 
        end
        else if (!stall_D) begin 
            ID_PC <= PC; 
            ID_Instr <= Instr; 
        end
    end

    wire [31:0] Reg_RD1, Reg_RD2, Imm_Ext;
    wire ctrl_rf_we, ctrl_mem_we, ctrl_alu_src, ctrl_branch, ctrl_jump;
    wire [1:0] ctrl_wb_sel;
    wire [2:0] ctrl_imm_sel;
    wire [3:0] ctrl_alu_ctrl;

    controller CTRL (
        .opcode(ID_Instr[6:0]), .funct3(ID_Instr[14:12]), .funct7(ID_Instr[31:25]),
        .rf_we(ctrl_rf_we), .mem_we(ctrl_mem_we), .wb_sel(ctrl_wb_sel),
        .alu_src(ctrl_alu_src), .imm_sel(ctrl_imm_sel), .alu_ctrl(ctrl_alu_ctrl),
        .branch(ctrl_branch), .jump(ctrl_jump)
    );

    register_file RF (
        .clk(clk), .rst_n(rst_n), .we(WB_rf_we),
        .rs1(ID_Instr[19:15]), .rs2(ID_Instr[24:20]), .rd(WB_rd),
        .wd(WB_Write_Back_Data), .rd1(Reg_RD1), .rd2(Reg_RD2)
    );

    sign_extender SEXT (.inst(ID_Instr), .imm_sel(ctrl_imm_sel), .imm(Imm_Ext));

    reg EX_rf_we, EX_mem_we, EX_alu_src, EX_branch, EX_jump;
    reg [1:0] EX_wb_sel;
    reg [3:0] EX_alu_ctrl;
    reg [31:0] EX_PC, EX_RD1, EX_RD2, EX_Imm;
    reg [4:0] EX_rd, EX_rs1, EX_rs2;

    always @(posedge clk or negedge rst_n) begin
        if (!rst_n || flush_E) begin
            EX_rf_we<=0; 
            EX_mem_we<=0; 
            EX_wb_sel<=0; 
            EX_alu_src<=0; 
            EX_alu_ctrl<=0;
            EX_branch<=0; 
            EX_jump<=0; 
            EX_PC<=0; 
            EX_RD1<=0; 
            EX_RD2<=0; 
            EX_Imm<=0;
            EX_rd<=0; 
            EX_rs1<=0; 
            EX_rs2<=0;
        end else begin
            EX_rf_we<=ctrl_rf_we; 
            EX_mem_we<=ctrl_mem_we; 
            EX_wb_sel<=ctrl_wb_sel;
            EX_alu_src<=ctrl_alu_src; 
            EX_alu_ctrl<=ctrl_alu_ctrl;
            EX_branch<=ctrl_branch; 
            EX_jump<=ctrl_jump;
            EX_PC<=ID_PC; 
            EX_RD1<=Reg_RD1; 
            EX_RD2<=Reg_RD2; 
            EX_Imm<=Imm_Ext;
            EX_rd<=ID_Instr[11:7]; 
            EX_rs1<=ID_Instr[19:15]; 
            EX_rs2<=ID_Instr[24:20];
        end
    end

    wire [31:0] SrcA_Fwd, SrcB_Fwd, ALU_B, ALU_Result;
    wire Zero;
    reg  [31:0] MA_ALU_Result;

    assign SrcA_Fwd = (forward_a_E == 2'b10) ? MA_ALU_Result : 
                      (forward_a_E == 2'b01) ? WB_Write_Back_Data : EX_RD1;
    assign SrcB_Fwd = (forward_b_E == 2'b10) ? MA_ALU_Result : 
                      (forward_b_E == 2'b01) ? WB_Write_Back_Data : EX_RD2;

    assign ALU_B = (EX_alu_src) ? EX_Imm : SrcB_Fwd;

    alu ALU (.a(SrcA_Fwd), .b(ALU_B), .alu_ctrl(EX_alu_ctrl), .result(ALU_Result), .zero(Zero));

    assign PC_Target_E = EX_PC + EX_Imm;
    assign pc_src_E = (EX_branch && Zero);
    assign jump_E = EX_jump;

    reg MA_rf_we, MA_mem_we;
    reg [1:0] MA_wb_sel;
    reg [31:0] MA_Write_Data, MA_PC_Plus4;
    reg [4:0] MA_rd;

    always @(posedge clk or negedge rst_n) begin
        if (!rst_n) begin
            MA_rf_we<=0; 
            MA_mem_we<=0; 
            MA_wb_sel<=0; 
            MA_ALU_Result<=0; 
            MA_Write_Data<=0; 
            MA_rd<=0; 
            MA_PC_Plus4<=0;
        end else begin
            MA_rf_we<=EX_rf_we; 
            MA_mem_we<=EX_mem_we; 
            MA_wb_sel<=EX_wb_sel;
            MA_ALU_Result<=ALU_Result; 
            MA_Write_Data<=SrcB_Fwd; 
            MA_rd<=EX_rd; 
            MA_PC_Plus4<=EX_PC+4;
        end
    end

    wire [31:0] Mem_Read_Data;
    data_mem DMEM (.clk(clk), .we(MA_mem_we), .addr(MA_ALU_Result), .wd(MA_Write_Data), .rd(Mem_Read_Data));

    reg WB_rf_we;
    reg [1:0] WB_wb_sel;
    reg [31:0] WB_Mem_Data, WB_ALU_Result, WB_PC_Plus4;
    reg [4:0] WB_rd;
    wire [31:0] WB_Write_Back_Data;

    always @(posedge clk or negedge rst_n) begin
        if (!rst_n) begin
            WB_rf_we<=0; 
            WB_wb_sel<=0; 
            WB_Mem_Data<=0; 
            WB_ALU_Result<=0; 
            WB_rd<=0; 
            WB_PC_Plus4<=0;
        end else begin
            WB_rf_we<=MA_rf_we; 
            WB_wb_sel<=MA_wb_sel; 
            WB_Mem_Data<=Mem_Read_Data;
            WB_ALU_Result<=MA_ALU_Result; 
            WB_rd<=MA_rd; 
            WB_PC_Plus4<=MA_PC_Plus4;
        end
    end

    assign WB_Write_Back_Data = (WB_wb_sel == 2'b01) ? WB_Mem_Data : 
                                (WB_wb_sel == 2'b10) ? WB_PC_Plus4 : WB_ALU_Result;

    hazard_unit HAZARD (
        .rs1_E(EX_rs1), .rs2_E(EX_rs2), .rd_M(MA_rd), .rd_W(WB_rd),
        .reg_write_M(MA_rf_we), .reg_write_W(WB_rf_we),
        .rs1_D(ID_Instr[19:15]), .rs2_D(ID_Instr[24:20]), .rd_E(EX_rd),
        .wb_sel_E(EX_wb_sel), .pc_src_E(pc_src_E), .jump_E(jump_E),
        .forward_a_E(forward_a_E), .forward_b_E(forward_b_E),
        .stall_F(stall_F), .stall_D(stall_D), .flush_D(flush_D), .flush_E(flush_E)
    );

endmodule

tb_rv_pl.v
`include "rv_pl.v"

`timescale 1ns/1ps

module tb_rv_pl;
    reg clk, rst_n;

    rv_pl DUT (
        .clk(clk),
        .rst_n(rst_n)
    );

    initial begin
        clk = 0;
        forever #5 clk = ~clk;
    end

    initial begin
        $dumpfile("wave_pl.vcd");
        $dumpvars(0, tb_rv_pl);

        $readmemh("test.mem", DUT.IMEM.RAM);

        rst_n = 0;
        #20 rst_n = 1;

        #200;
        
        $display("x1 = %d", DUT.RF.regs[1]);
        $display("x2 = %d", DUT.RF.regs[2]);
        $display("x3 = %d", DUT.RF.regs[3]);
        
        $finish;
    end
endmodule

wave_pl.vcd
$date
	Mon Jan 12 02:37:06 2026
$end
$version
	Icarus Verilog
$end
$timescale
	1ps
$end
$scope module tb_rv_pl $end
$var reg 1 ! clk $end
$var reg 1 " rst_n $end
$scope module DUT $end
$var wire 1 ! clk $end
$var wire 1 # jump_E $end
$var wire 1 $ pc_src_E $end
$var wire 1 " rst_n $end
$var wire 1 % stall_F $end
$var wire 1 & stall_D $end
$var wire 2 ' forward_b_E [1:0] $end
$var wire 2 ( forward_a_E [1:0] $end
$var wire 1 ) flush_E $end
$var wire 1 * flush_D $end
$var wire 2 + ctrl_wb_sel [1:0] $end
$var wire 1 , ctrl_rf_we $end
$var wire 1 - ctrl_mem_we $end
$var wire 1 . ctrl_jump $end
$var wire 3 / ctrl_imm_sel [2:0] $end
$var wire 1 0 ctrl_branch $end
$var wire 1 1 ctrl_alu_src $end
$var wire 4 2 ctrl_alu_ctrl [3:0] $end
$var wire 1 3 Zero $end
$var wire 32 4 WB_Write_Back_Data [31:0] $end
$var wire 32 5 SrcB_Fwd [31:0] $end
$var wire 32 6 SrcA_Fwd [31:0] $end
$var wire 32 7 Reg_RD2 [31:0] $end
$var wire 32 8 Reg_RD1 [31:0] $end
$var wire 32 9 PC_Target_E [31:0] $end
$var wire 32 : PC_Plus4 [31:0] $end
$var wire 32 ; PC_Next [31:0] $end
$var wire 32 < Mem_Read_Data [31:0] $end
$var wire 32 = Instr [31:0] $end
$var wire 32 > Imm_Ext [31:0] $end
$var wire 32 ? ALU_Result [31:0] $end
$var wire 32 @ ALU_B [31:0] $end
$var reg 32 A EX_Imm [31:0] $end
$var reg 32 B EX_PC [31:0] $end
$var reg 32 C EX_RD1 [31:0] $end
$var reg 32 D EX_RD2 [31:0] $end
$var reg 4 E EX_alu_ctrl [3:0] $end
$var reg 1 F EX_alu_src $end
$var reg 1 G EX_branch $end
$var reg 1 # EX_jump $end
$var reg 1 H EX_mem_we $end
$var reg 5 I EX_rd [4:0] $end
$var reg 1 J EX_rf_we $end
$var reg 5 K EX_rs1 [4:0] $end
$var reg 5 L EX_rs2 [4:0] $end
$var reg 2 M EX_wb_sel [1:0] $end
$var reg 32 N ID_Instr [31:0] $end
$var reg 32 O ID_PC [31:0] $end
$var reg 32 P MA_ALU_Result [31:0] $end
$var reg 32 Q MA_PC_Plus4 [31:0] $end
$var reg 32 R MA_Write_Data [31:0] $end
$var reg 1 S MA_mem_we $end
$var reg 5 T MA_rd [4:0] $end
$var reg 1 U MA_rf_we $end
$var reg 2 V MA_wb_sel [1:0] $end
$var reg 32 W PC [31:0] $end
$var reg 32 X WB_ALU_Result [31:0] $end
$var reg 32 Y WB_Mem_Data [31:0] $end
$var reg 32 Z WB_PC_Plus4 [31:0] $end
$var reg 5 [ WB_rd [4:0] $end
$var reg 1 \ WB_rf_we $end
$var reg 2 ] WB_wb_sel [1:0] $end
$scope module ALU $end
$var wire 32 ^ a [31:0] $end
$var wire 4 _ alu_ctrl [3:0] $end
$var wire 32 ` b [31:0] $end
$var reg 32 a result [31:0] $end
$var reg 1 3 zero $end
$upscope $end
$scope module CTRL $end
$var wire 3 b funct3 [2:0] $end
$var wire 7 c funct7 [6:0] $end
$var wire 7 d opcode [6:0] $end
$var reg 4 e alu_ctrl [3:0] $end
$var reg 1 1 alu_src $end
$var reg 1 0 branch $end
$var reg 3 f imm_sel [2:0] $end
$var reg 1 . jump $end
$var reg 1 - mem_we $end
$var reg 1 , rf_we $end
$var reg 2 g wb_sel [1:0] $end
$upscope $end
$scope module DMEM $end
$var wire 32 h addr [31:0] $end
$var wire 1 ! clk $end
$var wire 32 i rd [31:0] $end
$var wire 32 j wd [31:0] $end
$var wire 1 S we $end
$upscope $end
$scope module HAZARD $end
$var wire 1 * flush_D $end
$var wire 1 ) flush_E $end
$var wire 1 # jump_E $end
$var wire 1 k lw_stall $end
$var wire 1 $ pc_src_E $end
$var wire 5 l rd_E [4:0] $end
$var wire 5 m rd_M [4:0] $end
$var wire 5 n rd_W [4:0] $end
$var wire 1 U reg_write_M $end
$var wire 1 \ reg_write_W $end
$var wire 5 o rs1_D [4:0] $end
$var wire 5 p rs1_E [4:0] $end
$var wire 5 q rs2_D [4:0] $end
$var wire 5 r rs2_E [4:0] $end
$var wire 1 & stall_D $end
$var wire 1 % stall_F $end
$var wire 2 s wb_sel_E [1:0] $end
$var reg 2 t forward_a_E [1:0] $end
$var reg 2 u forward_b_E [1:0] $end
$upscope $end
$scope module IMEM $end
$var wire 32 v addr [31:0] $end
$var wire 32 w inst [31:0] $end
$upscope $end
$scope module RF $end
$var wire 1 ! clk $end
$var wire 5 x rd [4:0] $end
$var wire 5 y rs1 [4:0] $end
$var wire 5 z rs2 [4:0] $end
$var wire 1 " rst_n $end
$var wire 32 { wd [31:0] $end
$var wire 1 \ we $end
$var wire 32 | rd2 [31:0] $end
$var wire 32 } rd1 [31:0] $end
$var integer 32 ~ i [31:0] $end
$upscope $end
$scope module SEXT $end
$var wire 3 !" imm_sel [2:0] $end
$var wire 32 "" inst [31:0] $end
$var reg 32 #" imm [31:0] $end
$upscope $end
$upscope $end
$upscope $end
$enddefinitions $end
$comment Show the parameter values. $end
$dumpall
$end
#0
$dumpvars
b0 #"
b0 ""
b0 !"
b100000 ~
b0 }
b0 |
b0 {
b0 z
b0 y
b0 x
b100000000000010010011 w
b0 v
b0 u
b0 t
b0 s
b0 r
b0 q
b0 p
b0 o
b0 n
b0 m
b0 l
0k
b0 j
bx i
b0 h
b0 g
b0 f
b0 e
b0 d
b0 c
b0 b
b0 a
b0 `
b0 _
b0 ^
b0 ]
0\
b0 [
b0 Z
b0 Y
b0 X
b0 W
b0 V
0U
b0 T
0S
b0 R
b0 Q
b0 P
b0 O
b0 N
b0 M
b0 L
b0 K
0J
b0 I
0H
0G
0F
b0 E
b0 D
b0 C
b0 B
b0 A
b0 @
b0 ?
b0 >
b100000000000010010011 =
bx <
b100 ;
b100 :
b0 9
b0 8
b0 7
b0 6
b0 5
b0 4
13
b0 2
01
00
b0 /
0.
0-
0,
b0 +
0*
0)
b0 (
b0 '
0&
0%
0$
0#
0"
0!
$end
#5000
1!
#10000
b100000 ~
0!
#15000
1!
#20000
0!
1"
#25000
11
1,
b10011 d
b1 z
b1 q
b1 >
b1 #"
b1000 ;
b1000000000000100010011 =
b1000000000000100010011 w
bx Y
b100 Q
b100000000000010010011 N
b100000000000010010011 ""
b1000 :
b100 W
b100 v
1!
#30000
0!
#35000
03
b1 ?
b1 a
b1100 ;
b1000001000000110110011 =
b1000001000000110110011 w
b10 z
b10 q
b10 >
b10 #"
b1 @
b1 `
b1100 :
b1000 W
b1000 v
b1000000000000100010011 N
b1000000000000100010011 ""
b100 O
b1 L
b1 r
b1 I
b1 l
b1 9
b1 A
1F
1J
b100 Z
1!
#40000
0!
#45000
b10 ?
b10 a
01
1,
b10 @
b10 `
b110011 d
b1 y
b1 o
b10000 ;
b1100011000001000110011 =
b1100011000001000110011 w
b1 T
b1 m
b1 P
b1 h
1U
b10 L
b10 r
b10 I
b10 l
b10 A
b110 9
b100 B
b1000001000000110110011 N
b1000001000000110110011 ""
b1000 O
b10000 :
b1100 W
b1100 v
1!
#50000
0!
#55000
b1 6
b1 ^
03
b11 ?
b11 a
b1 4
b1 {
b10 5
b10100 ;
b1010001010000011 =
b1010001010000011 w
b11 y
b11 z
b11 o
b11 q
b11 >
b11 #"
b10 @
b10 `
b10 '
b10 u
b1 (
b1 t
b10100 :
b10000 W
b10000 v
b1100011000001000110011 N
b1100011000001000110011 ""
b1100 O
b1 K
b1 p
b11 I
b11 l
b1010 9
b1000 B
0F
b1000 Q
b10 T
b10 m
b10 P
b10 h
b1 [
b1 n
b1 x
b1 X
1\
1!
#60000
0!
#65000
b110 ?
b110 a
b10 4
b10 {
b11 @
b11 `
b11 6
b11 ^
b1 +
b1 g
11
1,
b1 8
b1 }
b11 5
b10 (
b10 t
b11 d
b10 b
b1 y
b0 z
b1 o
b0 q
b0 >
b0 #"
b11000 ;
b10000101000001010110011 =
b10000101000001010110011 w
b1000 Z
b10 [
b10 n
b10 x
b10 X
b1100 Q
b11 T
b11 m
b10 R
b10 j
b11 P
b11 h
b11 L
b11 r
b11 K
b11 p
b100 I
b100 l
b11 A
b1111 9
b1100 B
b1010001010000011 N
b1010001010000011 ""
b10000 O
b11000 :
b10100 W
b10100 v
1!
#70000
0!
#75000
1)
1%
1&
1k
01
b0 +
b0 g
1,
b0 8
b0 }
03
b1 ?
b1 a
b11 4
b11 {
b11100 ;
b11000101001010001100011 =
b11000101001010001100011 w
b110011 d
b0 b
b101 y
b100 z
b101 o
b100 q
b100 >
b100 #"
b0 @
b0 `
b1 6
b1 ^
b0 5
b0 '
b0 u
b0 (
b0 t
b11100 :
b11000 W
b11000 v
b10000101000001010110011 N
b10000101000001010110011 ""
b10100 O
b0 L
b0 r
b1 K
b1 p
b101 I
b101 l
b0 A
b1 C
b10000 9
b10000 B
1F
b1 M
b1 s
b10000 Q
b100 T
b100 m
b11 R
b11 j
b110 P
b110 h
b1100 Z
b11 [
b11 n
b11 x
b11 X
1!
#80000
0!
#85000
0)
13
b0 ?
b0 a
b110 4
b110 {
b0 6
b0 ^
0%
0&
0k
b10000 Z
b100 [
b100 n
b100 x
b110 X
b10100 Q
b101 T
b101 m
b0 R
b0 j
b1 P
b1 h
b1 V
b0 K
b0 p
b0 I
b0 l
b0 C
b0 9
b0 B
0F
b0 M
b0 s
0J
1!
#90000
b110 7
b110 |
0!
#95000
x3
bx ?
bx a
b110 @
b110 `
bx 6
bx ^
10
b1 2
b1 e
b10 /
b10 f
b10 !"
0,
b0 7
b0 |
b110 5
b100000 ;
b11111110110111111111000001101111 =
b11111110110111111111000001101111 w
b1100011 d
b1 b
b110 z
b110 q
b1000 >
b1000 #"
b1 (
b1 t
bx 4
bx {
b100000 :
b11100 W
b11100 v
b11000101001010001100011 N
b11000101001010001100011 ""
b11000 O
b100 L
b100 r
b101 K
b101 p
b101 I
b101 l
b100 A
b110 D
b11000 9
b10100 B
1J
b100 Q
b0 T
b0 m
b0 P
b0 h
b0 V
0U
b10100 Z
b101 [
b101 n
b101 x
b1 X
b1 ]
1!
#100000
bx 8
bx }
0!
#105000
b0 @
b0 `
x)
b0 5
x*
1.
b10 +
b10 g
1,
00
b0 2
b0 e
b100 /
b100 f
b100 !"
b0 8
b0 }
b0 4
b0 {
b10 (
b10 t
x$
b1101111 d
b111 b
b1111111 c
b11111 y
b1101 z
b11111 o
b1101 q
b11111111111111111111111111101100 >
b11111111111111111111111111101100 #"
b100x00 ;
b1100010011 =
b1100010011 w
b100 Z
b0 [
b0 n
b0 x
b0 X
b0 ]
0\
b11000 Q
b101 T
b101 m
b110 R
b110 j
bx P
bx h
1U
b110 L
b110 r
b1000 I
b1000 l
b1000 A
b0 D
bx C
b100000 9
b11000 B
1G
b1 E
b1 _
0J
b11111110110111111111000001101111 N
b11111110110111111111000001101111 ""
b11100 O
b100100 :
b100000 W
b100000 v
1!
#110000
0!
#115000
13
b0 ?
b0 a
11
0.
b0 /
b0 f
b0 !"
b0 +
b0 g
1,
bx 4
bx {
b0 6
b0 ^
bx =
bx w
b10011 d
b0 b
b0 c
b0 y
b0 z
b0 o
b0 q
b0 >
b0 #"
b1000 ;
1*
1)
0$
b0 (
b0 t
bx :
b100x00 W
b100x00 v
b1100010011 N
b1100010011 ""
b100000 O
b1101 L
b1101 r
b11111 K
b11111 p
b0 I
b0 l
b11111111111111111111111111101100 A
b0 C
b1000 9
b11100 B
1#
0G
b0 E
b0 _
b10 M
b10 s
1J
b11100 Q
b1000 T
b1000 m
b0 R
b0 j
0U
b11000 Z
b101 [
b101 n
b101 x
bx X
1\
1!
#120000
0!
#125000
01
0,
b1100 ;
0*
0)
b0 d
b1000001000000110110011 =
b1000001000000110110011 w
b11100 Z
b1000 [
b1000 n
b1000 x
0\
b100000 Q
b0 T
b0 m
b0 P
b0 h
b10 V
1U
b0 L
b0 r
b0 K
b0 p
b0 A
b0 9
b0 B
0#
b0 M
b0 s
0J
b0 N
b0 ""
b0 O
b1100 :
b1000 W
b1000 v
1!
#130000
0!
#135000
1,
b1 8
b1 }
b10 7
b10 |
b100000 4
b100000 {
b10000 ;
b1100011000001000110011 =
b1100011000001000110011 w
b110011 d
b1 y
b10 z
b1 o
b10 q
b10 >
b10 #"
b10000 :
b1100 W
b1100 v
b1000001000000110110011 N
b1000001000000110110011 ""
b1000 O
b100 Q
b0 V
0U
b100000 Z
b0 [
b0 n
b0 x
b0 X
b10 ]
1\
1!
#140000
0!
#145000
b10 @
b10 `
03
b11 ?
b11 a
b0 4
b0 {
b10 5
b1 6
b1 ^
b11 8
b11 }
b11 7
b11 |
b11 y
b11 z
b11 o
b11 q
b11 >
b11 #"
b10100 ;
b1010001010000011 =
b1010001010000011 w
b100 Z
b0 ]
0\
b10 L
b10 r
b1 K
b1 p
b11 I
b11 l
b10 A
b10 D
b1 C
b1010 9
b1000 B
1J
b1100011000001000110011 N
b1100011000001000110011 ""
b1100 O
b10100 :
b10000 W
b10000 v
1!
#150000
0!
#155000
b11 @
b11 `
b110 ?
b110 a
b1 +
b1 g
11
1,
b1 8
b1 }
b0 7
b0 |
b11 5
b11 6
b11 ^
b11000 ;
b10000101000001010110011 =
b10000101000001010110011 w
b11 d
b10 b
b1 y
b0 z
b1 o
b0 q
b0 >
b0 #"
b10 '
b10 u
b10 (
b10 t
b11000 :
b10100 W
b10100 v
b1010001010000011 N
b1010001010000011 ""
b10000 O
b11 L
b11 r
b11 K
b11 p
b100 I
b100 l
b11 A
b11 D
b11 C
b1111 9
b1100 B
b1100 Q
b11 T
b11 m
b10 R
b10 j
b11 P
b11 h
1U
1!
#160000
0!
#165000
1)
b11 4
b11 {
b1 ?
b1 a
1%
1&
1k
01
b0 +
b0 g
1,
bx 8
bx }
b110 7
b110 |
b1 6
b1 ^
b0 5
b0 '
b0 u
b0 (
b0 t
b0 @
b0 `
b110011 d
b0 b
b101 y
b100 z
b101 o
b100 q
b100 >
b100 #"
b11100 ;
b11000101001010001100011 =
b11000101001010001100011 w
b1100 Z
b11 [
b11 n
b11 x
b11 X
1\
b10000 Q
b100 T
b100 m
b11 R
b11 j
b110 P
b110 h
b0 L
b0 r
b1 K
b1 p
b101 I
b101 l
b0 A
b0 D
b1 C
b10000 9
b10000 B
1F
b1 M
b1 s
b10000101000001010110011 N
b10000101000001010110011 ""
b10100 O
b11100 :
b11000 W
b11000 v
1!
#170000
0!
#175000
0)
13
b0 ?
b0 a
b0 6
b0 ^
0%
0&
0k
b110 4
b110 {
b0 K
b0 p
b0 I
b0 l
b0 C
b0 9
b0 B
0F
b0 M
b0 s
0J
b10100 Q
b101 T
b101 m
b0 R
b0 j
b1 P
b1 h
b1 V
b10000 Z
b100 [
b100 n
b100 x
b110 X
1!
#180000
0!
#185000
b110 @
b110 `
x3
bx ?
bx a
b110 5
bx 6
bx ^
10
b1 2
b1 e
b10 /
b10 f
b10 !"
0,
b0 7
b0 |
bx 4
bx {
b1 (
b1 t
b1100011 d
b1 b
b110 z
b110 q
b1000 >
b1000 #"
b100000 ;
b11111110110111111111000001101111 =
b11111110110111111111000001101111 w
b10100 Z
b101 [
b101 n
b101 x
b1 X
b1 ]
b100 Q
b0 T
b0 m
b0 P
b0 h
b0 V
0U
b100 L
b100 r
b101 K
b101 p
b101 I
b101 l
b100 A
b110 D
bx C
b11000 9
b10100 B
1J
b11000101001010001100011 N
b11000101001010001100011 ""
b11000 O
b100000 :
b11100 W
b11100 v
1!
#190000
0!
#195000
b0 @
b0 `
x)
1.
b10 +
b10 g
1,
00
b0 2
b0 e
b100 /
b100 f
b100 !"
b0 8
b0 }
b0 5
x*
b100x00 ;
b1100010011 =
b1100010011 w
b1101111 d
b111 b
b1111111 c
b11111 y
b1101 z
b11111 o
b1101 q
b11111111111111111111111111101100 >
b11111111111111111111111111101100 #"
x$
b0 4
b0 {
b10 (
b10 t
b100100 :
b100000 W
b100000 v
b11111110110111111111000001101111 N
b11111110110111111111000001101111 ""
b11100 O
b110 L
b110 r
b1000 I
b1000 l
b1000 A
b0 D
b100000 9
b11000 B
1G
b1 E
b1 _
0J
b11000 Q
b101 T
b101 m
b110 R
b110 j
bx P
bx h
1U
b100 Z
b0 [
b0 n
b0 x
b0 X
b0 ]
0\
1!
#200000
0!
